[
  {
    "titulo": "Associar operadora",
    "url": "https://alf.globo.com/6828?url=https://globoplay.globo.com/tv-globo/ao-vivo/7832875/"
  },
  {
    "titulo": "Autoclassificação etária: livre\nAL\n\n11:30 - 14:44\n\nÉ de Casa",
    "url": "https://globoplay.globo.com/tv-globo/ao-vivo/7832875/"
  },
  {
    "titulo": "12:00 - 12:59\n\nGlobo Repórter",
    "url": "https://globoplay.globo.com/globonews/ao-vivo/6461772/"
  },
  {
    "titulo": "Autoclassificação etária: 12\nA12\n\n12:28 - 12:58\n\nVila, A\n\nHalloween",
    "url": "https://globoplay.globo.com/multishow/ao-vivo/9479865/"
  },
  {
    "titulo": "11:41 - 12:43\n\nCampeonato Brasileiro Feminino De Futebol\n\nPalmeiras X Santos",
    "url": "https://globoplay.globo.com/sportv/ao-vivo/9045469/"
  },
  {
    "titulo": "12:22 - 12:52\n\nCampeonato Brasileiro de Futebol\n\nRemo X Vasco",
    "url": "https://globoplay.globo.com/premiere/ao-vivo/9553134/"
  },
  {
    "titulo": "Autoclassificação etária: 10\nA10\n\n12:31 - 13:15\n\nInfiltrado Na Cozinha\n\nO Peixe Fora d'água",
    "url": "https://globoplay.globo.com/gnt/ao-vivo/9311314/"
  },
  {
    "titulo": "Autoclassificação etária: 12\nA12\n\n12:38 - 13:26\n\nPenso Em Ti\n\nCapítulo 23",
    "url": "https://globoplay.globo.com/globoplay-novelas/ao-vivo/8904966/"
  },
  {
    "titulo": "Sinal gratuito\n\nAo vivo\n\nAgora\n\nCBN Ao Vivo SP",
    "url": "https://globoplay.globo.com/cbn-sp/ao-vivo/9212712/"
  },
  {
    "titulo": "Sinal gratuito\n\nAo vivo\n\nAgora\n\nCBN Ao Vivo RJ",
    "url": "https://globoplay.globo.com/cbn-rj/ao-vivo/9212676/"
  }
]