[
  {
    "titulo": "Associar operadora",
    "url": "https://alf.globo.com/6828?url=https://globoplay.globo.com/tv-globo/ao-vivo/7832875/"
  },
  {
    "titulo": "Autoclassificação etária: livre\nAL\n\n07:55 - 08:24\n\nAuto Esporte",
    "url": "https://globoplay.globo.com/tv-globo/ao-vivo/7832875/"
  },
  {
    "titulo": "Ao vivo\n\n08:00 - 08:59\n\nJornal GloboNews",
    "url": "https://globoplay.globo.com/globonews/ao-vivo/6461772/"
  },
  {
    "titulo": "Classificação etária: 12\n12\n\n07:45 - 08:12\n\nChapolin\n\nOs Duendes",
    "url": "https://globoplay.globo.com/multishow/ao-vivo/9479865/"
  },
  {
    "titulo": "07:54 - 08:24\n\nCampeonato Brasileiro De Futebol\n\nRemo X Cruzeiro",
    "url": "https://globoplay.globo.com/sportv/ao-vivo/9045469/"
  },
  {
    "titulo": "07:50 - 08:19\n\nBrasileirão - Cruzeiro X Grêmio - 18042026\n\nAthletico-PR X Vitória",
    "url": "https://globoplay.globo.com/premiere/ao-vivo/9553134/"
  },
  {
    "titulo": "Classificação etária: 14\n14\n\n08:00 - 08:07\n\nMomento Que História É Essa, Porchat?\n\nFelipe Araújo + Carlos Gil + Ticiane Pinheiro",
    "url": "https://globoplay.globo.com/gnt/ao-vivo/9311314/"
  },
  {
    "titulo": "Classificação etária: 14\n14\n\n07:57 - 08:40\n\nVale Tudo",
    "url": "https://globoplay.globo.com/globoplay-novelas/ao-vivo/8904966/"
  },
  {
    "titulo": "Sinal gratuito\n\nAo vivo\n\nAgora\n\nCBN Ao Vivo SP",
    "url": "https://globoplay.globo.com/cbn-sp/ao-vivo/9212712/"
  },
  {
    "titulo": "Sinal gratuito\n\nAo vivo\n\nAgora\n\nCBN Ao Vivo RJ",
    "url": "https://globoplay.globo.com/cbn-rj/ao-vivo/9212676/"
  }
]