[
  {
    "titulo": "Associar operadora",
    "url": "https://alf.globo.com/6828?url=https://globoplay.globo.com/tv-globo/ao-vivo/7832875/"
  },
  {
    "titulo": "00:20 - 01:24\n\nTrês Graças",
    "url": "https://globoplay.globo.com/tv-globo/ao-vivo/7832875/"
  },
  {
    "titulo": "Ao vivo\n\n01:00 - 01:59\n\nJornal das Dez",
    "url": "https://globoplay.globo.com/globonews/ao-vivo/6461772/"
  },
  {
    "titulo": "Autoclassificação etária: 12\nA12\n\n01:04 - 01:33\n\nMelhores Momentos Lollapalooza\n\nLollapalooza 2026 - Viagra Boys",
    "url": "https://globoplay.globo.com/multishow/ao-vivo/9479865/"
  },
  {
    "titulo": "Ao vivo\n\n23:59 - 02:29\n\nCampeonato Brasileiro De Futebol Sub-20\n\nCorinthians X Santos",
    "url": "https://globoplay.globo.com/sportv/ao-vivo/9045469/"
  },
  {
    "titulo": "01:04 - 01:34\n\nCampeonato Brasileiro De Futebol\n\nRemo X Vasco",
    "url": "https://globoplay.globo.com/premiere/ao-vivo/9553134/"
  },
  {
    "titulo": "Classificação etária: 14\n14\n\n01:13 - 02:19\n\nQue História É Essa, Porchat?\n\nAlex Atala + Juliana Paiva + Filipe Toledo",
    "url": "https://globoplay.globo.com/gnt/ao-vivo/9311314/"
  },
  {
    "titulo": "Autoclassificação etária: 12\nA12\n\n00:48 - 01:40\n\nPenso Em Ti\n\nCapítulo 10",
    "url": "https://globoplay.globo.com/globoplay-novelas/ao-vivo/8904966/"
  },
  {
    "titulo": "Sinal gratuito\n\nAo vivo\n\nAgora\n\nCBN Ao Vivo SP",
    "url": "https://globoplay.globo.com/cbn-sp/ao-vivo/9212712/"
  },
  {
    "titulo": "Sinal gratuito\n\nAo vivo\n\nAgora\n\nCBN Ao Vivo RJ",
    "url": "https://globoplay.globo.com/cbn-rj/ao-vivo/9212676/"
  },
  {
    "titulo": "Ao vivo\n\nAgora\n\nAcompanhe a Casa",
    "url": "https://globoplay.globo.com/bbb-26-acompanhe-a-casa/ao-vivo/244881/"
  },
  {
    "titulo": "Ao vivo\n\nAgora\n\nAcompanhe a Casa 2",
    "url": "https://globoplay.globo.com/bbb-26-acompanhe-a-casa-2/ao-vivo/772202/"
  },
  {
    "titulo": "Ao vivo\n\nAgora\n\nMosaico",
    "url": "https://globoplay.globo.com/bbb-26-mosaico-bbb/ao-vivo/10101606/"
  },
  {
    "titulo": "Ao vivo\n\nAgora\n\nSegue o Líder",
    "url": "https://globoplay.globo.com/bbb-26-cozinha-2/ao-vivo/244887/"
  },
  {
    "titulo": "Ao vivo\n\nAgora\n\nSala Sonho de Ser Milionário",
    "url": "https://globoplay.globo.com/bbb-26-academia-nivea/ao-vivo/2254993/"
  },
  {
    "titulo": "Ao vivo\n\nAgora\n\nQuarto Sonho de Eternidade",
    "url": "https://globoplay.globo.com/bbb-26-quarto-sonho-de-eternidade/ao-vivo/772205/"
  },
  {
    "titulo": "Ao vivo\n\nAgora\n\nQuarto Sonho de Voar",
    "url": "https://globoplay.globo.com/bbb-26-quarto-sonho-de-voar/ao-vivo/6349747/"
  },
  {
    "titulo": "Ao vivo\n\nAgora\n\nCozinha",
    "url": "https://globoplay.globo.com/bbb-26-cozinha/ao-vivo/244889/"
  },
  {
    "titulo": "Ao vivo\n\nAgora\n\nBanheiro SUPER CIMED",
    "url": "https://globoplay.globo.com/bbb-26-banheiro-super-cimed/ao-vivo/2254996/"
  },
  {
    "titulo": "Ao vivo\n\nAgora\n\nSala Sonho de Ser Milionário",
    "url": "https://globoplay.globo.com/bbb-26-sala-sonho-de-ser-milionario/ao-vivo/2255000/"
  },
  {
    "titulo": "Ao vivo\n\nAgora\n\nCozinha",
    "url": "https://globoplay.globo.com/bbb-26-piscina/ao-vivo/244890/"
  },
  {
    "titulo": "Ao vivo\n\nAgora\n\nQuarto Sonho de Voar",
    "url": "https://globoplay.globo.com/bbb-26-quarto-sonho-de-voar-2/ao-vivo/2254997/"
  }
]